{
    "type": "minecraft:crafting_shaped",
    "group": "kitchen_drawer",
    "pattern": [
        "SDS",
        "CBC",
        "CCC"
    ],
    "key": {
        "S": {
            "item": "minecraft:stone"
        },
        "D": {
            "item": "minecraft:black_dye"
        },
        "C": {
            "item": "minecraft:terracotta"
        },
        "B": {
            "item": "minecraft:chest"
        }
    },
    "result": {
        "item": "cfm:black_kitchen_drawer",
        "count": 4
    }
}