{
  "parent": "minecraft:recipes/root",
  "rewards": {
    "recipes": [
      "cfm:acacia_mail_box"
    ]
  },
  "criteria": {
    "has_postbox": {
      "trigger": "minecraft:inventory_changed",
      "conditions": {
        "items": [
          {
            "item": "cfm:post_box"
          }
        ]
      }
    },
    "has_chest": {
      "trigger": "minecraft:inventory_changed",
      "conditions": {
        "items": [
          {
            "tag": "forge:chests/wooden"
          }
        ]
      }
    },
    "has_the_recipe": {
      "trigger": "minecraft:recipe_unlocked",
      "conditions": {
        "recipe": "cfm:acacia_mail_box"
      }
    }
  },
  "requirements": [
    [
      "has_postbox",
      "has_chest",
      "has_the_recipe"
    ]
  ]
}