{
    "__comment": "Model generated using MrCrayfish's Model Creator (https://mrcrayfish.com/tools?id=mc)",
    "textures": {
        "particle": "#color",
        "legs": "minecraft:block/light_gray_concrete",
        "mesh": "cfm:block/mesh"
    },
    "display": {
        "gui": {
            "rotation": [ 30, 45, 0 ],
            "translation": [ 0, 0, 0 ],
            "scale": [ 0.625, 0.625, 0.625 ]
        },
        "ground": {
            "rotation": [ 0, 0, 0 ],
            "translation": [ 0, 3, 0 ],
            "scale": [ 0.25, 0.25, 0.25 ]
        },
        "fixed": {
            "rotation": [ 0, 180, 0 ],
            "translation": [ 0, 0, 0 ],
            "scale": [ 1, 1, 1 ]
        },
        "head": {
            "rotation": [ 0, 180, 0 ],
            "translation": [ 0, 1, 0 ],
            "scale": [ 1, 1, 1 ]
        },
        "firstperson_righthand": {
            "rotation": [ 0, 315, 0 ],
            "translation": [ 0, 2.5, 0 ],
            "scale": [ 0.4, 0.4, 0.4 ]
        },
        "thirdperson_righthand": {
            "rotation": [ 75, 315, 0 ],
            "translation": [ 0, 2.5, 0 ],
            "scale": [ 0.375, 0.375, 0.375 ]
        }
    },
    "elements": [
        {
            "from": [ 1, 0, 2 ], 
            "to": [ 3, 11, 4 ], 
            "rotation": { "origin": [ 3, 8, 3 ], "axis": "y", "angle": -45.0 },
            "faces": {
                "north": { "texture": "#legs", "uv": [ 0, 0, 2, 11 ] },
                "east": { "texture": "#legs", "uv": [ 0, 0, 2, 11 ] },
                "south": { "texture": "#legs", "uv": [ 0, 0, 2, 11 ] },
                "west": { "texture": "#legs", "uv": [ 0, 0, 2, 11 ] },
                "down": { "texture": "#legs", "uv": [ 0, 0, 2, 2 ], "cullface": "down" }
            }
        },
        {
            "from": [ 1, 0, 12 ], 
            "to": [ 3, 11, 14 ], 
            "rotation": { "origin": [ 3, 8, 13 ], "axis": "y", "angle": 45.0 },
            "faces": {
                "north": { "texture": "#legs", "uv": [ 0, 0, 2, 11 ] },
                "east": { "texture": "#legs", "uv": [ 0, 0, 2, 11 ] },
                "south": { "texture": "#legs", "uv": [ 0, 0, 2, 11 ] },
                "west": { "texture": "#legs", "uv": [ 0, 0, 2, 11 ] },
                "down": { "texture": "#legs", "uv": [ 0, 0, 2, 2 ], "cullface": "down" }
            }
        },
        {
            "from": [ 0, 11, 2 ], 
            "to": [ 2, 16, 14 ], 
            "faces": {
                "east": { "texture": "#color", "uv": [ 0, 0, 12, 5 ] },
                "west": { "texture": "#color", "uv": [ 0, 0, 12, 5 ], "cullface": "west" },
                "up": { "texture": "#color", "uv": [ 0, 0, 2, 12 ] },
                "down": { "texture": "#color", "uv": [ 0, 0, 2, 12 ] }
            }
        },
        {
            "from": [ 14, 11, 2 ], 
            "to": [ 16, 16, 14 ], 
            "faces": {
                "east": { "texture": "#color", "uv": [ 0, 0, 12, 5 ], "cullface": "east" },
                "west": { "texture": "#color", "uv": [ 0, 0, 12, 5 ] },
                "up": { "texture": "#color", "uv": [ 0, 0, 2, 12 ] },
                "down": { "texture": "#color", "uv": [ 0, 0, 2, 12 ] }
            }
        },
        {
            "from": [ 2, 11, 0 ], 
            "to": [ 14, 16, 2 ], 
            "faces": {
                "north": { "texture": "#color", "uv": [ 0, 0, 12, 5 ], "cullface": "north" },
                "south": { "texture": "#color", "uv": [ 0, 0, 12, 5 ] },
                "up": { "texture": "#color", "uv": [ 0, 0, 12, 2 ] },
                "down": { "texture": "#color", "uv": [ 0, 0, 12, 2 ] }
            }
        },
        {
            "from": [ 2, 11, 14 ], 
            "to": [ 14, 16, 16 ], 
            "faces": {
                "north": { "texture": "#color", "uv": [ 0, 0, 12, 5 ] },
                "south": { "texture": "#color", "uv": [ 0, 0, 12, 5 ], "cullface": "south" },
                "up": { "texture": "#color", "uv": [ 0, 0, 12, 2 ] },
                "down": { "texture": "#color", "uv": [ 0, 0, 12, 2 ] }
            }
        },
        {
            "from": [ 2, 11, 2 ], 
            "to": [ 14, 12, 14 ], 
            "faces": {
                "up": { "texture": "#color", "uv": [ 2, 2, 14, 14 ] },
                "down": { "texture": "#color", "uv": [ 2, 2, 14, 14 ] }
            }
        },
        {
            "from": [ 2, 14.5, 2 ], 
            "to": [ 14, 15.5, 14 ], 
            "faces": {
                "up": { "texture": "#mesh", "uv": [ 0, 0, 15, 15 ] }
            }
        },
        {
            "from": [ 0, 11, 14 ], 
            "to": [ 2, 16, 16.829 ], 
            "rotation": { "origin": [ 0, 16, 14 ], "axis": "y", "angle": 45.0 },
            "faces": {
                "east": { "texture": "#color", "uv": [ 0, 0, 2.829, 5 ] },
                "south": { "texture": "#color", "uv": [ 0, 0, 2, 5 ] },
                "west": { "texture": "#color", "uv": [ 0, 0, 2.829, 5 ] },
                "up": { "texture": "#color", "uv": [ 0, 0, 2, 2.829 ] },
                "down": { "texture": "#color", "uv": [ 0, 0, 2, 2.829 ] }
            }
        },
        {
            "from": [ 2, 11, 0 ], 
            "to": [ 4, 16, 2.829 ], 
            "rotation": { "origin": [ 2, 16, 0 ], "axis": "y", "angle": -45.0 },
            "faces": {
                "east": { "texture": "#color", "uv": [ 0, 0, 2.829, 5 ] },
                "south": { "texture": "#color", "uv": [ 0, 0, 2, 5 ] },
                "west": { "texture": "#color", "uv": [ 0, 0, 2.829, 5 ] },
                "up": { "texture": "#color", "uv": [ 0, 0, 2, 2.829 ] },
                "down": { "texture": "#color", "uv": [ 0, 0, 2, 2.829 ] }
            }
        },
        {
            "from": [ 12, 11, 0 ], 
            "to": [ 14, 16, 2.829 ], 
            "rotation": { "origin": [ 14, 16, 0 ], "axis": "y", "angle": 45.0 },
            "faces": {
                "east": { "texture": "#color", "uv": [ 0, 0, 2.829, 5 ] },
                "south": { "texture": "#color", "uv": [ 0, 0, 2, 5 ] },
                "west": { "texture": "#color", "uv": [ 0, 0, 2.829, 5 ] },
                "up": { "texture": "#color", "uv": [ 0, 0, 2, 2.829 ] },
                "down": { "texture": "#color", "uv": [ 0, 0, 2, 2.829 ] }
            }
        },
        {
            "from": [ 14, 11, 14 ], 
            "to": [ 16, 16, 16.829 ], 
            "rotation": { "origin": [ 16, 16, 14 ], "axis": "y", "angle": -45.0 },
            "faces": {
                "east": { "texture": "#color", "uv": [ 0, 0, 2.829, 5 ] },
                "south": { "texture": "#color", "uv": [ 0, 0, 2, 5 ] },
                "west": { "texture": "#color", "uv": [ 0, 0, 2.829, 5 ] },
                "up": { "texture": "#color", "uv": [ 0, 0, 2, 2.829 ] },
                "down": { "texture": "#color", "uv": [ 0, 0, 2, 2.829 ] }
            }
        },
        {
            "from": [ 13, 0, 12 ], 
            "to": [ 15, 11, 14 ], 
            "rotation": { "origin": [ 13, 8, 13 ], "axis": "y", "angle": -45.0 },
            "faces": {
                "north": { "texture": "#legs", "uv": [ 0, 0, 2, 11 ] },
                "east": { "texture": "#legs", "uv": [ 0, 0, 2, 11 ] },
                "south": { "texture": "#legs", "uv": [ 0, 0, 2, 11 ] },
                "west": { "texture": "#legs", "uv": [ 0, 0, 2, 11 ] },
                "down": { "texture": "#legs", "uv": [ 0, 0, 2, 2 ], "cullface": "down" }
            }
        },
        {
            "from": [ 13, 0, 2 ], 
            "to": [ 15, 11, 4 ], 
            "rotation": { "origin": [ 13, 8, 3 ], "axis": "y", "angle": 45.0 },
            "faces": {
                "north": { "texture": "#legs", "uv": [ 0, 0, 2, 11 ] },
                "east": { "texture": "#legs", "uv": [ 0, 0, 2, 11 ] },
                "south": { "texture": "#legs", "uv": [ 0, 0, 2, 11 ] },
                "west": { "texture": "#legs", "uv": [ 0, 0, 2, 11 ] },
                "down": { "texture": "#legs", "uv": [ 0, 0, 2, 2 ], "cullface": "down" }
            }
        },
        {
            "from": [ 0, 4, 7.5 ], 
            "to": [ 16, 5, 8.5 ], 
            "rotation": { "origin": [ 8, 8, 8 ], "axis": "y", "angle": -45.0 },
            "faces": {
                "north": { "texture": "#legs", "uv": [ 0, 0, 16, 1 ] },
                "south": { "texture": "#legs", "uv": [ 0, 0, 16, 1 ] },
                "up": { "texture": "#legs", "uv": [ 0, 0, 16, 1 ] },
                "down": { "texture": "#legs", "uv": [ 0, 0, 16, 1 ] }
            }
        },
        {
            "from": [ 0, 4, 7.5 ], 
            "to": [ 16, 5, 8.5 ], 
            "rotation": { "origin": [ 8, 8, 8 ], "axis": "y", "angle": 45.0 },
            "faces": {
                "north": { "texture": "#legs", "uv": [ 0, 0, 16, 1 ] },
                "south": { "texture": "#legs", "uv": [ 0, 0, 16, 1 ] },
                "up": { "texture": "#legs", "uv": [ 0, 0, 16, 1 ] },
                "down": { "texture": "#legs", "uv": [ 0, 0, 16, 1 ] }
            }
        }
    ]
}